soldapi/__init__.py
soldapi/core/__init__.py
soldapi/core/qwork/__init__.py
soldapi/core/qwork/misc.py
soldapi-0.9.3.dist-info/LICENSE
soldapi-0.9.3.dist-info/METADATA
soldapi-0.9.3.dist-info/WHEEL
soldapi-0.9.3.dist-info/top_level.txt
soldapi-0.9.3.dist-info/RECORD
