Metadata-Version: 2.1
Name: soldapi
Version: 0.9.3
Summary: Solid Operational Long-term Dynamics API
Author-email: nphard001 <nphard001@gmail.com>
Keywords: api,python,utility
Classifier: Programming Language :: Python :: 3.10
Classifier: License :: OSI Approved :: MIT License
Classifier: Operating System :: OS Independent
Requires-Python: >=3.10
License-File: LICENSE
